PythonAnquanBianchengJiaocheng/README.md
PythonAnquanBianchengJiaocheng/__init__.py
PythonAnquanBianchengJiaocheng/__main__.py
PythonAnquanBianchengJiaocheng/file.epub
PythonAnquanBianchengJiaocheng/index.html
PythonAnquanBianchengJiaocheng/css/__init__.py
PythonAnquanBianchengJiaocheng/css/annotations.css
PythonAnquanBianchengJiaocheng/css/main.css
PythonAnquanBianchengJiaocheng/css/normalize.css
PythonAnquanBianchengJiaocheng/css/popup.css
PythonAnquanBianchengJiaocheng/font/__init__.py
PythonAnquanBianchengJiaocheng/font/fontello.eot
PythonAnquanBianchengJiaocheng/font/fontello.svg
PythonAnquanBianchengJiaocheng/font/fontello.ttf
PythonAnquanBianchengJiaocheng/font/fontello.woff
PythonAnquanBianchengJiaocheng/img/__init__.py
PythonAnquanBianchengJiaocheng/img/annotator-glyph-sprite.png
PythonAnquanBianchengJiaocheng/img/annotator-icon-sprite.png
PythonAnquanBianchengJiaocheng/img/apple-touch-icon.png
PythonAnquanBianchengJiaocheng/img/cancelfullscreen.png
PythonAnquanBianchengJiaocheng/img/close.png
PythonAnquanBianchengJiaocheng/img/fullscreen.png
PythonAnquanBianchengJiaocheng/img/loader.gif
PythonAnquanBianchengJiaocheng/img/menu-icon.png
PythonAnquanBianchengJiaocheng/img/save.png
PythonAnquanBianchengJiaocheng/img/saved.png
PythonAnquanBianchengJiaocheng/img/settings-s.png
PythonAnquanBianchengJiaocheng/img/settings.png
PythonAnquanBianchengJiaocheng/img/star.png
PythonAnquanBianchengJiaocheng/js/__init__.py
PythonAnquanBianchengJiaocheng/js/epub.js
PythonAnquanBianchengJiaocheng/js/epub.min.js
PythonAnquanBianchengJiaocheng/js/epub.min.map
PythonAnquanBianchengJiaocheng/js/hooks.min.js
PythonAnquanBianchengJiaocheng/js/hooks.min.map
PythonAnquanBianchengJiaocheng/js/reader.js
PythonAnquanBianchengJiaocheng/js/reader.js.map
PythonAnquanBianchengJiaocheng/js/reader.min.js
PythonAnquanBianchengJiaocheng/js/reader.min.map
PythonAnquanBianchengJiaocheng/js/hooks/__init__.py
PythonAnquanBianchengJiaocheng/js/hooks/extensions/__init__.py
python_anquan_biancheng_jiaocheng-2024.3.1.0.dist-info/METADATA
python_anquan_biancheng_jiaocheng-2024.3.1.0.dist-info/WHEEL
python_anquan_biancheng_jiaocheng-2024.3.1.0.dist-info/entry_points.txt
python_anquan_biancheng_jiaocheng-2024.3.1.0.dist-info/top_level.txt
python_anquan_biancheng_jiaocheng-2024.3.1.0.dist-info/RECORD
